{"data":{"program":{"category":{"name":"Développement"},"costsInter":[{"cost":2380.0}],"description":"Objectif de formation : Au terme de cette formation l'apprenant sera capable de créer des applications Web à l'aide de Bubble","durationInHours":28.0,"goals":[{"text":"Gérer un projet de développement sous Bubble en Low Code / No code"},{"text":"Créer des applications Web à l'aide de Bubble"},{"text":"Contrôler le niveau de sécurité de votre application Web"},{"text":"Décupler la performance de votre application Bubble"},{"text":"Publier et administrer votre application Web créée sous Bubble"}],"id":"1189080","image":{"url":"https://cdn.filestackcontent.com/bisabUwiSEivfeOlH0m7"},"name":"Bubble - Création d'applications Web No Code","steps":[{"substeps":[{"text":"Concept \"no-code\""},{"text":"Présentation de Bubble et de la notion de PaaS"},{"text":"Forces et faiblesses de Bubble"},{"text":"Positionnement de Bubble au sein de son marché"}],"text":"Introduction"},{"substeps":[{"text":"Inscription"},{"text":"Construction d'un projet"},{"text":"Éditeur d'interface"},{"text":"Gestionnaire de flux logiques et de base de données"},{"text":"Éditeur de styles"},{"text":"Bibliothèque de plug-ins"},{"text":"Paramétrage de l'application"},{"text":"Activité du serveur"}],"text":"Premiers pas avec l'outil"},{"substeps":[{"text":"Utilisateur & utilisateur actuel"},{"text":"Type de contenu d'une page ou d'un élément"},{"text":"Relation Parent / Enfant entre éléments"},{"text":"Groupe & groupe répétitif"},{"text":"Environnement test et environnement de production"}],"text":"Présentation des concepts de base pour l'utilisation de Bubble"},{"substeps":[{"text":"Création d'une interface utilisateur"},{"text":"Gestion de l'aspect responsive du site"},{"text":"Structuration de la base de données"},{"text":"Connexion de l'interface et la base de données"},{"text":"Création de flux de modification de données"},{"text":"Publication de l'application sur le Web"},{"text":"Implémentation d'une carte géographique"},{"text":"Configuration du module Google Maps"},{"text":"Liaison aux analytiques"},{"text":"Ajout d'un module de recherche"},{"text":"Présentation de la notion d'indexation de contenu"},{"text":"Type de recherches auxquelles répond Bubble"},{"text":"Déploiement d'un plug-in de recherche approximative pour des résultats plus pertinents"},{"text":"Utilisation de la recherche par secteur géographique"}],"text":"Création pas à pas d'un site"},{"substeps":[{"text":"Etat d'un élément"},{"text":"Serveur vs client"},{"text":"Concept de liste dans Bubble"},{"text":"Gestion des mots de passe dans Bubble"}],"text":"Concepts de niveau intermédiaire pour utiliser Bubble"},{"substeps":[{"text":"Conception d'une application à partir de scénarios utilisateurs"},{"text":"Créer une maquette avant de commencer le développement"},{"text":"Structurer une base de données prête pour la mise à échelle"},{"text":"Attribuer des tags et gérer des listes"},{"text":"Utiliser un plug-in de gestion de téléchargement"},{"text":"Améliorer l'expérience utilisateur avec des interactions visuelles"},{"text":"Créer un système de compte utilisateur"},{"text":"Créer une page ayant un type défini"},{"text":"Créer un système de vote"},{"text":"Rendre une interface multilingue"}],"text":"Conception pas à pas d'un site"},{"substeps":[{"text":"Mise en place d'une logique d'administration"},{"text":"Création de comptes ayant des droits spéciaux"},{"text":"Création d'une interface d'administration"}],"text":"Administration du contenu partagé"},{"substeps":[{"text":"Flux personnalisés & flux API"},{"text":"Concept de flux récursifs "},{"text":"Modification de liste"},{"text":"Dialoguer avec d'autres services grâce à l'API Connector"},{"text":"Comprendre ce qui impacte la performance"},{"text":"Les 3 niveaux de sécurité d'une application Bubble"}],"text":"Concepts avancés pour utiliser Bubble"},{"substeps":[{"text":"Utilisation d'un template de la marketplace Bubble"},{"text":"Création des flux logiques et des flux personnalisés"},{"text":"Création d'un système de notifications en utilisant un flux API"},{"text":"Création des notifications push avec OneSignal et l'API Connector"},{"text":"Définition des règles de sécurité côté serveur"},{"text":"Ajout des flux de sécurité côté client"},{"text":"Ajout des éléments de sécurité à l'interface"},{"text":"Visualisation les données sous forme de graphiques"}],"text":"Création pas à pas d'un CRM"},{"substeps":[{"text":"Mettre à jour le statut d'un prospect automatiquement après un temps donné"},{"text":"Concept de flux programmé"},{"text":"Comment annuler un flux programmé"},{"text":"L'intérêt des flux programmés"}],"text":"Gestion du statut d'un prospect"},{"substeps":[{"text":"Documenter la programmation dans Bubble"},{"text":"Gérer son projet en mode Agile comme un Scrum Master"},{"text":"La mise à l'échelle (scaling) avec Bubble"},{"text":"Les différents niveaux de forfait Bubble"},{"text":"Bubble et la RGPD"},{"text":"Les ressources pour continuer à progresser"},{"text":"La communauté des programmeurs Bubble"}],"text":"Conclusion"}]}}}